abloom/xxhash.h
abloom/__init__.py
abloom/_abloom.cpython-313-darwin.so
abloom/_abloom.c
abloom/_abloom.pyi
abloom/py.typed
abloom-1.0.0.dist-info/RECORD
abloom-1.0.0.dist-info/WHEEL
abloom-1.0.0.dist-info/entry_points.txt
abloom-1.0.0.dist-info/top_level.txt
abloom-1.0.0.dist-info/METADATA
abloom-1.0.0.dist-info/licenses/LICENSE
